nig/verilong/exp5/demux_switch/demux1to4.v
// 1-to-2 De-MUX using Switch Level Description
module demux1to2 (
    input  wire in,
    input  wire sel,
    output wire y0,
    output wire y1
);
    wire sel_n;
    
    // CMOS Not gate at switch level (can also use 'not' gate)
    not (sel_n, sel);

    // Using nmos switches as pass transistors: nmos(output, input, control)
    // If sel=0, y0 = in. If sel=1, y1 = in.
    nmos n1 (y0, in, sel_n);
    nmos n2 (y1, in, sel);

endmodule

// 1-to-4 De-MUX hierarchical design
module demux1to4 (
    input  wire in,
    input  wire [1:0] sel,
    output wire [3:0] y
);
    wire w0, w1;

    // First stage using sel[1]
    demux1to2 d_main (
        .in (in),
        .sel(sel[1]),
        .y0 (w0),
        .y1 (w1)
    );

    // Second stage using sel[0]
    demux1to2 d_sub0 (
        .in (w0),
        .sel(sel[0]),
        .y0 (y[0]),
        .y1 (y[1])
    );

    demux1to2 d_sub1 (
        .in (w1),
        .sel(sel[0]),
        .y0 (y[2]),
        .y1 (y[3])
    );

endmodule

nig/verilong/exp5/demux_switch/testbench.v
`timescale 1ns/1ps

module testbench;
    reg in;
    reg [1:0] sel;
    wire [3:0] y;

    demux1to4 uut (
        .in (in),
        .sel(sel),
        .y  (y)
    );

    integer i;

    initial begin
        $dumpfile("dump.vcd");
        $dumpvars(0, testbench);

        $display("Time	In	Sel	Y (3-2-1-0)");
        $monitor("%t	%b	%b	%b", $time, in, sel, y);

        // Set input to 1
        in = 1;

        // Iterate through all select lines
        for (i = 0; i < 4; i = i + 1) begin
            sel = i; #10;
        end

        // Set input to 0 and re-test
        in = 0;
        for (i = 0; i < 4; i = i + 1) begin
            sel = i; #10;
        end

        $finish;
    end
endmodule

nig/verilong/exp5/demux_switch/dump.vcd
$date
	Mon Mar 30 15:53:05 2026
$end
$version
	Icarus Verilog
$end
$timescale
	1ps
$end
$scope module testbench $end
$var wire 4 ! y [3:0] $end
$var reg 1 " in $end
$var reg 2 # sel [1:0] $end
$var integer 32 $ i [31:0] $end
$scope module uut $end
$var wire 1 " in $end
$var wire 2 % sel [1:0] $end
$var wire 4 & y [3:0] $end
$var wire 1 ' w1 $end
$var wire 1 ( w0 $end
$scope module d_main $end
$var wire 1 " in $end
$var wire 1 ) sel $end
$var wire 1 * sel_n $end
$var wire 1 ( y0 $end
$var wire 1 ' y1 $end
$upscope $end
$scope module d_sub0 $end
$var wire 1 ( in $end
$var wire 1 + sel $end
$var wire 1 , sel_n $end
$var wire 1 - y0 $end
$var wire 1 . y1 $end
$upscope $end
$scope module d_sub1 $end
$var wire 1 ' in $end
$var wire 1 / sel $end
$var wire 1 0 sel_n $end
$var wire 1 1 y0 $end
$var wire 1 2 y1 $end
$upscope $end
$upscope $end
$upscope $end
$enddefinitions $end
$comment Show the parameter values. $end
$dumpall
$end
#0
$dumpvars
z2
z1
10
0/
z.
1-
1,
0+
1*
0)
1(
z'
bz1 &
b0 %
b0 $
b0 #
1"
bz1 !
$end
#10000
z-
0,
z1
00
bz1z !
bz1z &
1.
1+
z2
1/
b1 #
b1 %
b1 $
#20000
z(
0*
z-
1,
10
bz1zz !
bz1zz &
11
1'
1)
z.
0+
z2
0/
b10 #
b10 %
b10 $
#30000
z-
0,
z1
00
b1zzz !
b1zzz &
z.
1+
12
1/
b11 #
b11 %
b11 $
#40000
1*
1,
10
0)
0+
0/
bz0 !
bz0 &
b0 #
b0 %
0-
z.
0(
z1
z2
z'
0"
b0 $
#50000
z-
0,
z1
00
bz0z !
bz0z &
0.
1+
z2
1/
b1 #
b1 %
b1 $
#60000
z(
0*
z-
1,
10
bz0zz !
bz0zz &
01
0'
1)
z.
0+
z2
0/
b10 #
b10 %
b10 $
#70000
z-
0,
z1
00
b0zzz !
b0zzz &
z.
1+
02
1/
b11 #
b11 %
b11 $
#80000
b100 $
