nig/verilong/exp4/divisibility_by_3/divisible_by_3.v
module divisible_by_3 (
    input  wire       clk,
    input  wire       reset,
    input  wire       serial_in,
    output reg  [7:0] shift_reg,
    output wire       is_divisible
);

    // Shift register to store the "moving" 8-bit number
    always @(posedge clk or posedge reset) begin
        if (reset) begin
            shift_reg <= 8'b0;
        end else begin
            shift_reg <= {shift_reg[6:0], serial_in};
        end
    end

    // Combinational logic to check divisibility by 3
    // A number N is divisible by 3 if (Sum_even_bits - Sum_odd_bits) mod 3 = 0
    // For 8 bits: (b0+b2+b4+b6) - (b1+b3+b5+b7) mod 3 = 0
    assign is_divisible = (shift_reg % 3 == 0);

endmodule

nig/verilong/exp4/divisibility_by_3/testbench.v
`timescale 1ns/1ps

module testbench;
    reg clk;
    reg reset;
    reg serial_in;
    wire [7:0] shift_reg;
    wire is_divisible;

    divisible_by_3 uut (
        .clk(clk),
        .reset(reset),
        .serial_in(serial_in),
        .shift_reg(shift_reg),
        .is_divisible(is_divisible)
    );

    // Clock generation
    initial clk = 0;
    always #5 clk = ~clk;

    integer i;
    reg [15:0] test_sequence = 16'b1101101001011001;

    initial begin
        $dumpfile("dump.vcd");
        $dumpvars(0, testbench);

        reset = 1; serial_in = 0; #10;
        reset = 0;

        $display("Time	Bit	Shift Reg	Decimal	Divisible by 3?");
        $monitor("%t	%b	%b	%d	%b", $time, serial_in, shift_reg, shift_reg, is_divisible);

        for (i = 15; i >= 0; i = i - 1) begin
            serial_in = test_sequence[i];
            #10;
        end

        // Additional test: Input multiple of 3
        // Let's shift in 12 (00001100)
        serial_in = 0; #10;
        serial_in = 0; #10;
        serial_in = 0; #10;
        serial_in = 0; #10;
        serial_in = 1; #10;
        serial_in = 1; #10;
        serial_in = 0; #10;
        serial_in = 0; #10;

        $finish;
    end
endmodule

nig/verilong/exp4/divisibility_by_3/dump.vcd
$date
	Mon Mar 30 15:49:29 2026
$end
$version
	Icarus Verilog
$end
$timescale
	1ps
$end
$scope module testbench $end
$var wire 8 ! shift_reg [7:0] $end
$var wire 1 " is_divisible $end
$var reg 1 # clk $end
$var reg 1 $ reset $end
$var reg 1 % serial_in $end
$var reg 16 & test_sequence [15:0] $end
$var integer 32 ' i [31:0] $end
$scope module uut $end
$var wire 1 # clk $end
$var wire 1 $ reset $end
$var wire 1 % serial_in $end
$var wire 1 " is_divisible $end
$var reg 8 ( shift_reg [7:0] $end
$upscope $end
$upscope $end
$enddefinitions $end
$comment Show the parameter values. $end
$dumpall
$end
#0
$dumpvars
b0 (
bx '
b1101101001011001 &
0%
1$
0#
1"
b0 !
$end
#5000
1#
#10000
0#
1%
b1111 '
0$
#15000
0"
b1 !
b1 (
1#
#20000
0#
b1110 '
#25000
1"
b11 !
b11 (
1#
#30000
0#
0%
b1101 '
#35000
b110 !
b110 (
1#
#40000
0#
1%
b1100 '
#45000
0"
b1101 !
b1101 (
1#
#50000
0#
b1011 '
#55000
1"
b11011 !
b11011 (
1#
#60000
0#
0%
b1010 '
#65000
b110110 !
b110110 (
1#
#70000
0#
1%
b1001 '
#75000
0"
b1101101 !
b1101101 (
1#
#80000
0#
0%
b1000 '
#85000
b11011010 !
b11011010 (
1#
#90000
0#
b111 '
#95000
1"
b10110100 !
b10110100 (
1#
#100000
0#
1%
b110 '
#105000
b1101001 !
b1101001 (
1#
#110000
0#
0%
b101 '
#115000
b11010010 !
b11010010 (
1#
#120000
0#
1%
b100 '
#125000
b10100101 !
b10100101 (
1#
#130000
0#
b11 '
#135000
b1001011 !
b1001011 (
1#
#140000
0#
0%
b10 '
#145000
b10010110 !
b10010110 (
1#
#150000
0#
b1 '
#155000
0"
b101100 !
b101100 (
1#
#160000
0#
1%
b0 '
#165000
b1011001 !
b1011001 (
1#
#170000
0#
0%
b11111111111111111111111111111111 '
#175000
b10110010 !
b10110010 (
1#
#180000
0#
#185000
b1100100 !
b1100100 (
1#
#190000
0#
#195000
b11001000 !
b11001000 (
1#
#200000
0#
#205000
1"
b10010000 !
b10010000 (
1#
#210000
0#
1%
#215000
b100001 !
b100001 (
1#
#220000
0#
#225000
0"
b1000011 !
b1000011 (
1#
#230000
0#
0%
#235000
b10000110 !
b10000110 (
1#
#240000
0#
#245000
1"
b1100 !
b1100 (
1#
