nig/verilong/exp1-a/structural/mux2to1.v
module mux2to1 (
    input  a, b, sel,
    output out
);
    wire not_sel, and_a, and_b;

    // Gate-level implementation (Structural)
    not (not_sel, sel);
    and (and_a, a, not_sel);
    and (and_b, b, sel);
    or  (out, and_a, and_b);

endmodule

nig/verilong/exp1-a/structural/mux8to1.v
module mux8to1 (
    input  [7:0] data,
    input  [2:0] sel,
    output       out
);
    wire m1, m2, m3, m4, m5, m6;

    // First layer: 4 muxes for the 8 data lines
    mux2to1 u1 (data[0], data[1], sel[0], m1);
    mux2to1 u2 (data[2], data[3], sel[0], m2);
    mux2to1 u3 (data[4], data[5], sel[0], m3);
    mux2to1 u4 (data[6], data[7], sel[0], m4);

    // Second layer: 2 muxes to combine the 4 inputs
    mux2to1 u5 (m1, m2, sel[1], m5);
    mux2to1 u6 (m3, m4, sel[1], m6);

    // Final layer: 1 mux to produce the final output
    mux2to1 u7 (m5, m6, sel[2], out);

endmodule

nig/verilong/exp1-a/behavioural/testbench.v
`timescale 1ns/1ps

module testbench;

    reg  [7:0] data;
    reg  [2:0] sel;
    wire       out;

    // Instantiate 8:1 MUX
    mux8to1 uut (
        .data(data),
        .sel (sel),
        .out (out)
    );

    integer i;

    initial begin
        $dumpfile("dump.vcd");
        $dumpvars(0, testbench);

        $display("Time\tSel\tData\t\tOut");
        $monitor("%t\t%d\t%b\t%b", $time, sel, data, out);

        // Pattern 1: Single bit high
        data = 8'b10101010;
        for (i = 0; i < 8; i = i + 1) begin
            sel = i; #10;
        end

        // Pattern 2: Different bits
        data = 8'b11001100;
        for (i = 0; i < 8; i = i + 1) begin
            sel = i; #10;
        end

        $finish;
    end

endmodule

nig/verilong/exp1-a/structural/dump.vcd
$date
	Mon Mar 30 14:45:40 2026
$end
$version
	Icarus Verilog
$end
$timescale
	1ps
$end
$scope module testbench $end
$var wire 1 ! out $end
$var reg 8 " data [7:0] $end
$var reg 3 # sel [2:0] $end
$var integer 32 $ i [31:0] $end
$scope module uut $end
$var wire 8 % data [7:0] $end
$var wire 3 & sel [2:0] $end
$var wire 1 ! out $end
$var wire 1 ' m6 $end
$var wire 1 ( m5 $end
$var wire 1 ) m4 $end
$var wire 1 * m3 $end
$var wire 1 + m2 $end
$var wire 1 , m1 $end
$scope module u1 $end
$var wire 1 - a $end
$var wire 1 . and_a $end
$var wire 1 / and_b $end
$var wire 1 0 b $end
$var wire 1 1 not_sel $end
$var wire 1 , out $end
$var wire 1 2 sel $end
$upscope $end
$scope module u2 $end
$var wire 1 3 a $end
$var wire 1 4 and_a $end
$var wire 1 5 and_b $end
$var wire 1 6 b $end
$var wire 1 7 not_sel $end
$var wire 1 + out $end
$var wire 1 8 sel $end
$upscope $end
$scope module u3 $end
$var wire 1 9 a $end
$var wire 1 : and_a $end
$var wire 1 ; and_b $end
$var wire 1 < b $end
$var wire 1 = not_sel $end
$var wire 1 * out $end
$var wire 1 > sel $end
$upscope $end
$scope module u4 $end
$var wire 1 ? a $end
$var wire 1 @ and_a $end
$var wire 1 A and_b $end
$var wire 1 B b $end
$var wire 1 C not_sel $end
$var wire 1 ) out $end
$var wire 1 D sel $end
$upscope $end
$scope module u5 $end
$var wire 1 , a $end
$var wire 1 E and_a $end
$var wire 1 F and_b $end
$var wire 1 + b $end
$var wire 1 G not_sel $end
$var wire 1 ( out $end
$var wire 1 H sel $end
$upscope $end
$scope module u6 $end
$var wire 1 * a $end
$var wire 1 I and_a $end
$var wire 1 J and_b $end
$var wire 1 ) b $end
$var wire 1 K not_sel $end
$var wire 1 ' out $end
$var wire 1 L sel $end
$upscope $end
$scope module u7 $end
$var wire 1 ( a $end
$var wire 1 M and_a $end
$var wire 1 N and_b $end
$var wire 1 ' b $end
$var wire 1 O not_sel $end
$var wire 1 ! out $end
$var wire 1 P sel $end
$upscope $end
$upscope $end
$upscope $end
$enddefinitions $end
$comment Show the parameter values. $end
$dumpall
$end
#0
$dumpvars
0P
1O
0N
0M
0L
1K
0J
0I
0H
1G
0F
0E
0D
1C
1B
0A
0@
0?
0>
1=
1<
0;
0:
09
08
17
16
05
04
03
02
11
10
0/
0.
0-
0,
0+
0*
0)
0(
0'
b0 &
b10101010 %
b0 $
b0 #
b10101010 "
0!
$end
#10000
1!
1M
1(
1'
1E
1I
1,
1+
1*
1)
01
1/
07
15
0=
1;
0C
1A
12
18
1>
1D
b1 #
b1 &
b1 $
#20000
0!
0M
0(
0'
0,
0+
0*
0)
0E
0I
11
0/
17
05
1=
0;
1C
0A
0G
0F
0K
0J
02
08
0>
0D
1H
1L
b10 #
b10 &
b10 $
#30000
1!
1M
1(
1'
1F
1J
1,
1+
1*
1)
01
1/
07
15
0=
1;
0C
1A
12
18
1>
1D
b11 #
b11 &
b11 $
#40000
0!
0,
0+
0*
0)
0E
0(
0I
0'
0M
11
0/
17
05
1=
0;
1C
0A
1G
0F
1K
0J
0O
0N
02
08
0>
0D
0H
0L
1P
b100 #
b100 &
b100 $
#50000
1!
1N
1(
1'
1E
1I
1,
1+
1*
1)
01
1/
07
15
0=
1;
0C
1A
12
18
1>
1D
b101 #
b101 &
b101 $
#60000
0!
0N
0(
0'
0,
0+
0*
0)
0E
0I
11
0/
17
05
1=
0;
1C
0A
0G
0F
0K
0J
02
08
0>
0D
1H
1L
b110 #
b110 &
b110 $
#70000
1!
1N
1(
1'
1F
1J
1,
1+
1*
1)
01
1/
07
15
0=
1;
0C
1A
12
18
1>
1D
b111 #
b111 &
b111 $
#80000
14
1+
1@
1)
0(
0'
0M
0!
0,
0*
11
17
05
1=
1C
0A
1G
0F
1K
0J
1O
0N
0/
0;
02
08
0>
0D
0H
0L
0P
00
13
0<
1?
b0 #
b0 &
b11001100 "
b11001100 %
b0 $
#90000
04
0@
01
07
15
0=
0C
1A
12
18
1>
1D
b1 #
b1 &
b1 $
#100000
1!
1M
14
1+
1@
1)
1(
1'
11
17
05
1=
1C
0A
0G
1F
0K
1J
02
08
0>
0D
1H
1L
b10 #
b10 &
b10 $
#110000
04
0@
01
07
15
0=
0C
1A
12
18
1>
1D
b11 #
b11 &
b11 $
#120000
0!
14
1+
1@
1)
0(
0'
0M
11
17
05
1=
1C
0A
1G
0F
1K
0J
0O
0N
02
08
0>
0D
0H
0L
1P
b100 #
b100 &
b100 $
#130000
04
0@
01
07
15
0=
0C
1A
12
18
1>
1D
b101 #
b101 &
b101 $
#140000
1!
1N
14
1+
1@
1)
1(
1'
11
17
05
1=
1C
0A
0G
1F
0K
1J
02
08
0>
0D
1H
1L
b110 #
b110 &
b110 $
#150000
04
0@
01
07
15
0=
0C
1A
12
18
1>
1D
b111 #
b111 &
b111 $
#160000
b1000 $
