nig/verilong/exp1-a/behavioural/mux8to1.v
module mux8to1 (
    input  [7:0] data,
    input  [2:0] sel,
    output reg   out
);
    // Behavioral logic using a case block
    always @(*) begin
        case (sel)
            3'b000: out = data[0];
            3'b001: out = data[1];
            3'b010: out = data[2];
            3'b011: out = data[3];
            3'b100: out = data[4];
            3'b101: out = data[5];
            3'b110: out = data[6];
            3'b111: out = data[7];
            default: out = 1'b0;
        endcase
    end
endmodule

nig/verilong/exp1-a/behavioural/testbench.v
`timescale 1ns/1ps

module testbench;

    reg  [7:0] data;
    reg  [2:0] sel;
    wire       out;

    // Instantiate 8:1 MUX
    mux8to1 uut (
        .data(data),
        .sel (sel),
        .out (out)
    );

    integer i;

    initial begin
        $dumpfile("dump.vcd");
        $dumpvars(0, testbench);

        $display("Time\tSel\tData\t\tOut");
        $monitor("%t\t%d\t%b\t%b", $time, sel, data, out);

        // Pattern 1: Single bit high
        data = 8'b10101010;
        for (i = 0; i < 8; i = i + 1) begin
            sel = i; #10;
        end

        // Pattern 2: Different bits
        data = 8'b11001100;
        for (i = 0; i < 8; i = i + 1) begin
            sel = i; #10;
        end

        $finish;
    end

endmodule

nig/verilong/exp1-a/behavioural/dump.vcd
$date
	Mon Mar 30 14:45:40 2026
$end
$version
	Icarus Verilog
$end
$timescale
	1ps
$end
$scope module testbench $end
$var wire 1 ! out $end
$var reg 8 " data [7:0] $end
$var reg 3 # sel [2:0] $end
$var integer 32 $ i [31:0] $end
$scope module uut $end
$var wire 8 % data [7:0] $end
$var wire 3 & sel [2:0] $end
$var reg 1 ! out $end
$upscope $end
$upscope $end
$enddefinitions $end
$comment Show the parameter values. $end
$dumpall
$end
#0
$dumpvars
b0 &
b10101010 %
b0 $
b0 #
b10101010 "
0!
$end
#10000
1!
b1 #
b1 &
b1 $
#20000
0!
b10 #
b10 &
b10 $
#30000
1!
b11 #
b11 &
b11 $
#40000
0!
b100 #
b100 &
b100 $
#50000
1!
b101 #
b101 &
b101 $
#60000
0!
b110 #
b110 &
b110 $
#70000
1!
b111 #
b111 &
b111 $
#80000
0!
b0 #
b0 &
b11001100 "
b11001100 %
b0 $
#90000
b1 #
b1 &
b1 $
#100000
1!
b10 #
b10 &
b10 $
#110000
b11 #
b11 &
b11 $
#120000
0!
b100 #
b100 &
b100 $
#130000
b101 #
b101 &
b101 $
#140000
1!
b110 #
b110 &
b110 $
#150000
b111 #
b111 &
b111 $
#160000
b1000 $
