nig/verilong/exp3/mux4to1_dataflow/mux4to1.v
module mux4to1 (
    input  [3:0] d,
    input  [1:0] s,
    output       y
);
    // Dataflow modeling using bit-selection
    assign y = d[s];
endmodule

nig/verilong/exp3/mux4to1_dataflow/testbench.v
`timescale 1ns/1ps

module testbench;
    reg  [3:0] d;
    reg  [1:0] s;
    wire       y;

    mux4to1 uut (
        .d(d),
        .s(s),
        .y(y)
    );

    integer i;

    initial begin
        $dumpfile("dump.vcd");
        $dumpvars(0, testbench);

        $display("Time	S	D		Y");
        $monitor("%t	%b	%b	%b", $time, s, d, y);

        d = 4'b1010;
        for (i = 0; i < 4; i = i + 1) begin
            s = i; #10;
        end

        d = 4'b1100;
        for (i = 0; i < 4; i = i + 1) begin
            s = i; #10;
        end

        $finish;
    end
endmodule

nig/verilong/exp3/mux4to1_dataflow/dump.vcd
$date
	Mon Mar 30 15:45:41 2026
$end
$version
	Icarus Verilog
$end
$timescale
	1ps
$end
$scope module testbench $end
$var wire 1 ! y $end
$var reg 4 " d [3:0] $end
$var reg 2 # s [1:0] $end
$var integer 32 $ i [31:0] $end
$scope module uut $end
$var wire 4 % d [3:0] $end
$var wire 2 & s [1:0] $end
$var wire 1 ! y $end
$upscope $end
$upscope $end
$enddefinitions $end
$comment Show the parameter values. $end
$dumpall
$end
#0
$dumpvars
b0 &
b1010 %
b0 $
b0 #
b1010 "
0!
$end
#10000
1!
b1 #
b1 &
b1 $
#20000
0!
b10 #
b10 &
b10 $
#30000
1!
b11 #
b11 &
b11 $
#40000
0!
b0 #
b0 &
b1100 "
b1100 %
b0 $
#50000
b1 #
b1 &
b1 $
#60000
1!
b10 #
b10 &
b10 $
#70000
b11 #
b11 &
b11 $
#80000
b100 $
