nig/verilong/exp2/exp2-behavioural/barrel_shifter.v
module barrel_shifter (
    input  [7:0] data_in,   // 8-bit binary input
    input  [2:0] select,    // 3-bit select lines (shift amount 0-7)
    input        control,   // 1-bit control: 0 for Logical Shift Left, 1 for Rotate Left
    output [7:0] data_out
);

    wire [7:0] stage0, stage1;

    // Stage 0: Shift/Rotate by 1 bit
    // If control=0: {i6,i5,i4,i3,i2,i1,i0, 0}
    // If control=1: {i6,i5,i4,i3,i2,i1,i0, i7}
    assign stage0 = select[0] ? (control ? {data_in[6:0], data_in[7]}   : {data_in[6:0], 1'b0}) : data_in;

    // Stage 1: Shift/Rotate by 2 bits
    assign stage1 = select[1] ? (control ? {stage0[5:0], stage0[7:6]}  : {stage0[5:0], 2'b00}) : stage0;

    // Stage 2: Shift/Rotate by 4 bits
    assign data_out = select[2] ? (control ? {stage1[3:0], stage1[7:4]} : {stage1[3:0], 4'b0000}) : stage1;

endmodule

nig/verilong/exp2/exp2-behavioural/testbench.v
`timescale 1ns/1ps

module testbench;

    reg  [7:0] data_in;
    reg  [2:0] select;
    reg        control;
    wire [7:0] data_out;

    // Instantiate Barrel Shifter
    barrel_shifter uut (
        .data_in (data_in),
        .select  (select),
        .control (control),
        .data_out(data_out)
    );

    integer i, c, p;
    reg [7:0] patterns [0:2];

    initial begin
        $dumpfile("dump.vcd");
        $dumpvars(0, testbench);

        // Define test patterns
        patterns[0] = 8'b1010_1100; // Original pattern
        patterns[1] = 8'b1000_0000; // Single MSB bit
        patterns[2] = 8'b0101_0101; // Alternating bits

        $display("Time\tCtrl\tSel\tInput\t\tOutput");
        $monitor("%t\t%b\t%d\t%b\t%b", $time, control, select, data_in, data_out);

        for (p = 0; p < 3; p = p + 1) begin
            data_in = patterns[p];
            $display("\n=== Testing Data Pattern: %b ===", data_in);
            
            for (c = 0; c < 2; c = c + 1) begin
                control = c;
                $display("--- Mode: %s ---", control ? "Rotate Left" : "Logical Shift Left");
                for (i = 0; i < 8; i = i + 1) begin
                    select = i; #10;
                end
            end
        end

        $finish;
    end

endmodule

nig/verilong/exp2/exp2-behavioural/dump.vcd
$date
	Mon Mar 30 15:23:06 2026
$end
$version
	Icarus Verilog
$end
$timescale
	1ps
$end
$scope module testbench $end
$var wire 8 ! data_out [7:0] $end
$var reg 1 " control $end
$var reg 8 # data_in [7:0] $end
$var reg 3 $ select [2:0] $end
$var integer 32 % c [31:0] $end
$var integer 32 & i [31:0] $end
$var integer 32 ' p [31:0] $end
$scope module uut $end
$var wire 1 " control $end
$var wire 8 ( data_in [7:0] $end
$var wire 3 ) select [2:0] $end
$var wire 8 * stage1 [7:0] $end
$var wire 8 + stage0 [7:0] $end
$var wire 8 , data_out [7:0] $end
$upscope $end
$upscope $end
$enddefinitions $end
$comment Show the parameter values. $end
$dumpall
$end
#0
$dumpvars
b10101100 ,
b10101100 +
b10101100 *
b0 )
b10101100 (
b0 '
b0 &
b0 %
b0 $
b10101100 #
0"
b10101100 !
$end
#10000
b1011000 !
b1011000 ,
b1011000 *
b1011000 +
b1 $
b1 )
b1 &
#20000
b10110000 !
b10110000 ,
b10101100 +
b10110000 *
b10 $
b10 )
b10 &
#30000
b1100000 !
b1100000 ,
b1100000 *
b1011000 +
b11 $
b11 )
b11 &
#40000
b10101100 +
b10101100 *
b11000000 !
b11000000 ,
b100 $
b100 )
b100 &
#50000
b10000000 !
b10000000 ,
b1011000 *
b1011000 +
b101 $
b101 )
b101 &
#60000
b0 !
b0 ,
b10101100 +
b10110000 *
b110 $
b110 )
b110 &
#70000
b1100000 *
b1011000 +
b111 $
b111 )
b111 &
#80000
b10101100 +
b10101100 *
b10101100 !
b10101100 ,
b0 $
b0 )
1"
b1 %
b0 &
#90000
b1011001 !
b1011001 ,
b1011001 *
b1011001 +
b1 $
b1 )
b1 &
#100000
b10110010 !
b10110010 ,
b10101100 +
b10110010 *
b10 $
b10 )
b10 &
#110000
b1100101 !
b1100101 ,
b1100101 *
b1011001 +
b11 $
b11 )
b11 &
#120000
b10101100 +
b10101100 *
b11001010 !
b11001010 ,
b100 $
b100 )
b100 &
#130000
b10010101 !
b10010101 ,
b1011001 *
b1011001 +
b101 $
b101 )
b101 &
#140000
b101011 !
b101011 ,
b10101100 +
b10110010 *
b110 $
b110 )
b110 &
#150000
b1010110 !
b1010110 ,
b1100101 *
b1011001 +
b111 $
b111 )
b111 &
#160000
b10000000 +
b10000000 *
b10000000 !
b10000000 ,
b0 $
b0 )
0"
b10000000 #
b10000000 (
b1 '
b0 %
b0 &
#170000
b0 !
b0 ,
b0 *
b0 +
b1 $
b1 )
b1 &
#180000
b10000000 +
b10 $
b10 )
b10 &
#190000
b0 +
b11 $
b11 )
b11 &
#200000
b10000000 *
b10000000 +
b100 $
b100 )
b100 &
#210000
b0 *
b0 +
b101 $
b101 )
b101 &
#220000
b10000000 +
b110 $
b110 )
b110 &
#230000
b0 +
b111 $
b111 )
b111 &
#240000
b10000000 !
b10000000 ,
b10000000 *
b10000000 +
b0 $
b0 )
1"
b1 %
b0 &
#250000
b1 !
b1 ,
b1 *
b1 +
b1 $
b1 )
b1 &
#260000
b10 !
b10 ,
b10000000 +
b10 *
b10 $
b10 )
b10 &
#270000
b100 !
b100 ,
b100 *
b1 +
b11 $
b11 )
b11 &
#280000
b10000000 +
b10000000 *
b1000 !
b1000 ,
b100 $
b100 )
b100 &
#290000
b10000 !
b10000 ,
b1 *
b1 +
b101 $
b101 )
b101 &
#300000
b100000 !
b100000 ,
b10000000 +
b10 *
b110 $
b110 )
b110 &
#310000
b1000000 !
b1000000 ,
b100 *
b1 +
b111 $
b111 )
b111 &
#320000
b1010101 *
b1010101 !
b1010101 ,
b1010101 +
b0 $
b0 )
0"
b1010101 #
b1010101 (
b10 '
b0 %
b0 &
#330000
b10101010 !
b10101010 ,
b10101010 *
b10101010 +
b1 $
b1 )
b1 &
#340000
b1010100 !
b1010100 ,
b1010101 +
b1010100 *
b10 $
b10 )
b10 &
#350000
b10101000 !
b10101000 ,
b10101000 *
b10101010 +
b11 $
b11 )
b11 &
#360000
b1010101 +
b1010101 *
b1010000 !
b1010000 ,
b100 $
b100 )
b100 &
#370000
b10100000 !
b10100000 ,
b10101010 *
b10101010 +
b101 $
b101 )
b101 &
#380000
b1000000 !
b1000000 ,
b1010101 +
b1010100 *
b110 $
b110 )
b110 &
#390000
b10000000 !
b10000000 ,
b10101000 *
b10101010 +
b111 $
b111 )
b111 &
#400000
b1010101 +
b1010101 *
b1010101 !
b1010101 ,
b0 $
b0 )
1"
b1 %
b0 &
#410000
b10101010 !
b10101010 ,
b10101010 *
b10101010 +
b1 $
b1 )
b1 &
#420000
b1010101 !
b1010101 ,
b1010101 *
b1010101 +
b10 $
b10 )
b10 &
#430000
b10101010 !
b10101010 ,
b10101010 *
b10101010 +
b11 $
b11 )
b11 &
#440000
b1010101 !
b1010101 ,
b1010101 *
b1010101 +
b100 $
b100 )
b100 &
#450000
b10101010 !
b10101010 ,
b10101010 *
b10101010 +
b101 $
b101 )
b101 &
#460000
b1010101 !
b1010101 ,
b1010101 *
b1010101 +
b110 $
b110 )
b110 &
#470000
b10101010 !
b10101010 ,
b10101010 *
b10101010 +
b111 $
b111 )
b111 &
#480000
b11 '
b10 %
b1000 &
